{"eventHeader": {"locationSource": "gpsrsu", "asdFirmwareVersion": "ASD-SW_v4.3.3.0", "eventAlertActive": false, "eventAlertSent": true, "eventAlertHeard": false, "hostVehID": "07D4FB56", "targetVehID": "00000000", "triggerHVSeqNum": 20, "triggerTVSeqNum": 16384, "eventType": "spdcomp", "parameters": {"recordingROI": "300", "timeRecordBefore": "20", "timeRecordFollow": "10", "timeRecordResolution": "resEverySec", "minSpdThreshold": "2", "excessiveSpd": "3", "excessiveSpdTime": "0", "regulatorySpeed": "11"}, "grpId": 23, "eventStatus": "Obfuscated", "eventTimeBin": "2021-04-FRI-AM", "eventLocationBin": "CV-MN-2wayAve", "weatherCondition": "MostlyCloudy", "airTemperature": 50, "precipitation1Hr": "0.00", "windSpeed": 4}, "bsmList": [{"eventMsgSeqNum": 1, "bsmRecord": {"msgHeader": {"myRFLevel": 0, "authenticated": true}, "bsmMsg": {"coreData": {"msgCnt": 29, "id": "07D4FB56", "accuracy": {"semiMajor": 102, "semiMinor": 2, "orientation": 54117}, "transmission": "forwardGears", "angle": 127, "accelSet": {"long_mpss": 0.4, "lat_mpss": -0.3, "vert_mpss": -0.259, "yaw_dps": 0.14}, "brakes": {"wheelBrakes": "00", "traction": "unavailable", "abs": "unavailable", "scs": "unavailable", "brakeBoost": "unavailable", "auxBrakes": "unavailable"}, "size": {"width": 175, "length": 470}, "X_m": 176.755, "Y_m": 221.41, "Z_m": 0.0, "T_s": -18.927, "speed_mps": 13.46, "heading_deg": 207.275}, "partII": [{"partII-Id": 0, "partII-Value": {"pathHistory": {"crumbData": [{"xOffset_m": -266.687, "yOffset_m": -344.83, "zOffset_m": 0.0, "tOffset_s": -4.09}, {"xOffset_m": -361.601, "yOffset_m": -531.628, "zOffset_m": -2.1, "tOffset_s": -24.5}]}, "pathPrediction": {"radiusOfCurve": 32767, "confidence": 197}}}, {"partII-Id": 2, "partII-Value": {"classification": 10, "vehicleData": {"height": 29, "mass": 37}}}]}}}, {"eventMsgSeqNum": 2, "bsmRecord": {"msgHeader": {"myRFLevel": 0, "authenticated": true}, "bsmMsg": {"coreData": {"msgCnt": 40, "id": "07D4FB56", "accuracy": {"semiMajor": 110, "semiMinor": 2, "orientation": 54155}, "transmission": "forwardGears", "angle": 127, "accelSet": {"long_mpss": 0.5, "lat_mpss": -0.3, "vert_mpss": -0.259, "yaw_dps": -0.17}, "brakes": {"wheelBrakes": "00", "traction": "unavailable", "abs": "unavailable", "scs": "unavailable", "brakeBoost": "unavailable", "auxBrakes": "unavailable"}, "size": {"width": 175, "length": 470}, "X_m": 169.595, "Y_m": 208.24, "Z_m": 0.0, "T_s": -17.827, "speed_mps": 13.98, "heading_deg": 207.475}, "partII": [{"partII-Id": 0, "partII-Value": {"pathHistory": {"crumbData": [{"xOffset_m": -266.687, "yOffset_m": -344.83, "zOffset_m": 0.0, "tOffset_s": -5.19}, {"xOffset_m": -361.601, "yOffset_m": -531.628, "zOffset_m": -2.1, "tOffset_s": -25.59}]}, "pathPrediction": {"radiusOfCurve": 32767, "confidence": 174}}}, {"partII-Id": 2, "partII-Value": {"classification": 10, "vehicleData": {"height": 29, "mass": 37}}}]}}}, {"eventMsgSeqNum": 3, "bsmRecord": {"msgHeader": {"myRFLevel": 0, "authenticated": true}, "bsmMsg": {"coreData": {"msgCnt": 50, "id": "07D4FB56", "accuracy": {"semiMajor": 116, "semiMinor": 2, "orientation": 54161}, "transmission": "forwardGears", "angle": 127, "accelSet": {"long_mpss": 0.46, "lat_mpss": -0.34, "vert_mpss": -0.259, "yaw_dps": 0.0}, "brakes": {"wheelBrakes": "00", "traction": "unavailable", "abs": "unavailable", "scs": "unavailable", "brakeBoost": "unavailable", "auxBrakes": "unavailable"}, "size": {"width": 175, "length": 470}, "X_m": 162.976, "Y_m": 195.858, "Z_m": 0.0, "T_s": -16.827, "speed_mps": 14.24, "heading_deg": 207.513}, "partII": [{"partII-Id": 0, "partII-Value": {"pathHistory": {"crumbData": [{"xOffset_m": -266.687, "yOffset_m": -344.83, "zOffset_m": 0.0, "tOffset_s": -6.2}, {"xOffset_m": -361.601, "yOffset_m": -531.628, "zOffset_m": -2.1, "tOffset_s": -26.6}]}, "pathPrediction": {"radiusOfCurve": 32767, "confidence": 200}}}, {"partII-Id": 2, "partII-Value": {"classification": 10, "vehicleData": {"height": 29, "mass": 37}}}]}}}, {"eventMsgSeqNum": 4, "bsmRecord": {"msgHeader": {"myRFLevel": 0, "authenticated": true}, "bsmMsg": {"coreData": {"msgCnt": 60, "id": "07D4FB56", "accuracy": {"semiMajor": 122, "semiMinor": 2, "orientation": 54132}, "transmission": "forwardGears", "angle": 127, "accelSet": {"long_mpss": 0.5, "lat_mpss": -0.18, "vert_mpss": -0.259, "yaw_dps": 0.13}, "brakes": {"wheelBrakes": "00", "traction": "unavailable", "abs": "unavailable", "scs": "unavailable", "brakeBoost": "unavailable", "auxBrakes": "unavailable"}, "size": {"width": 175, "length": 470}, "X_m": 156.137, "Y_m": 183.209, "Z_m": 0.0, "T_s": -15.827, "speed_mps": 14.62, "heading_deg": 207.35}, "partII": [{"partII-Id": 0, "partII-Value": {"pathHistory": {"crumbData": [{"xOffset_m": -266.687, "yOffset_m": -344.841, "zOffset_m": 0.0, "tOffset_s": -7.19}, {"xOffset_m": -361.601, "yOffset_m": -531.639, "zOffset_m": -2.1, "tOffset_s": -27.6}]}, "pathPrediction": {"radiusOfCurve": 32767, "confidence": 163}}}, {"partII-Id": 2, "partII-Value": {"classification": 10, "vehicleData": {"height": 29, "mass": 37}}}]}}}, {"eventMsgSeqNum": 5, "bsmRecord": {"msgHeader": {"myRFLevel": 0, "authenticated": true}, "bsmMsg": {"coreData": {"msgCnt": 70, "id": "07D4FB56", "accuracy": {"semiMajor": 127, "semiMinor": 2, "orientation": 54139}, "transmission": "forwardGears", "angle": 127, "accelSet": {"long_mpss": 0.34, "lat_mpss": -0.28, "vert_mpss": -0.259, "yaw_dps": -0.16}, "brakes": {"wheelBrakes": "00", "traction": "unavailable", "abs": "unavailable", "scs": "unavailable", "brakeBoost": "unavailable", "auxBrakes": "unavailable"}, "size": {"width": 175, "length": 470}, "X_m": 148.935, "Y_m": 170.338, "Z_m": 0.0, "T_s": -14.827, "speed_mps": 14.9, "heading_deg": 207.4}, "partII": [{"partII-Id": 0, "partII-Value": {"pathHistory": {"crumbData": [{"xOffset_m": -266.687, "yOffset_m": -344.83, "zOffset_m": 0.0, "tOffset_s": -8.19}, {"xOffset_m": -361.601, "yOffset_m": -531.628, "zOffset_m": -2.1, "tOffset_s": -28.6}]}, "pathPrediction": {"radiusOfCurve": 32767, "confidence": 200}}}, {"partII-Id": 2, "partII-Value": {"classification": 10, "vehicleData": {"height": 29, "mass": 37}}}]}}}, {"eventMsgSeqNum": 6, "bsmRecord": {"msgHeader": {"myRFLevel": 0, "authenticated": true}, "bsmMsg": {"coreData": {"msgCnt": 80, "id": "07D4FB56", "accuracy": {"semiMajor": 132, "semiMinor": 2, "orientation": 54193}, "transmission": "forwardGears", "angle": 127, "accelSet": {"long_mpss": 0.25, "lat_mpss": -0.14, "vert_mpss": -0.259, "yaw_dps": 0.32}, "brakes": {"wheelBrakes": "00", "traction": "unavailable", "abs": "unavailable", "scs": "unavailable", "brakeBoost": "unavailable", "auxBrakes": "unavailable"}, "size": {"width": 175, "length": 470}, "X_m": 141.293, "Y_m": 157.279, "Z_m": 0.0, "T_s": -13.827, "speed_mps": 15.32, "heading_deg": 207.688}, "partII": [{"partII-Id": 0, "partII-Value": {"pathHistory": {"crumbData": [{"xOffset_m": -209.071, "yOffset_m": -238.477, "zOffset_m": 0.0, "tOffset_s": -0.19}, {"xOffset_m": -266.687, "yOffset_m": -344.83, "zOffset_m": 0.0, "tOffset_s": -9.19}, {"xOffset_m": -361.601, "yOffset_m": -531.628, "zOffset_m": -2.1, "tOffset_s": -29.6}]}, "pathPrediction": {"radiusOfCurve": 32767, "confidence": 197}}}, {"partII-Id": 2, "partII-Value": {"classification": 10, "vehicleData": {"height": 29, "mass": 37}}}]}}}, {"eventMsgSeqNum": 7, "bsmRecord": {"msgHeader": {"myRFLevel": 0, "authenticated": true}, "bsmMsg": {"coreData": {"msgCnt": 90, "id": "07D4FB56", "accuracy": {"semiMajor": 136, "semiMinor": 2, "orientation": 54395}, "transmission": "forwardGears", "angle": 127, "accelSet": {"long_mpss": 0.28, "lat_mpss": 0.21, "vert_mpss": -0.259, "yaw_dps": 1.55}, "brakes": {"wheelBrakes": "00", "traction": "unavailable", "abs": "unavailable", "scs": "unavailable", "brakeBoost": "unavailable", "auxBrakes": "unavailable"}, "size": {"width": 175, "length": 470}, "X_m": 133.12, "Y_m": 144.108, "Z_m": 0.0, "T_s": -12.827, "speed_mps": 15.6, "heading_deg": 208.8}, "partII": [{"partII-Id": 0, "partII-Value": {"pathHistory": {"crumbData": [{"xOffset_m": -209.071, "yOffset_m": -238.477, "zOffset_m": 0.0, "tOffset_s": -1.19}, {"xOffset_m": -266.687, "yOffset_m": -344.83, "zOffset_m": 0.0, "tOffset_s": -10.19}, {"xOffset_m": -361.601, "yOffset_m": -531.628, "zOffset_m": -2.1, "tOffset_s": -30.6}]}, "pathPrediction": {"radiusOfCurve": 24368, "confidence": 134}}}, {"partII-Id": 2, "partII-Value": {"classification": 10, "vehicleData": {"height": 29, "mass": 37}}}]}}}, {"eventMsgSeqNum": 8, "bsmRecord": {"msgHeader": {"myRFLevel": 0, "authenticated": true}, "bsmMsg": {"coreData": {"msgCnt": 100, "id": "07D4FB56", "accuracy": {"semiMajor": 139, "semiMinor": 2, "orientation": 54810}, "transmission": "forwardGears", "angle": 127, "accelSet": {"long_mpss": -0.16, "lat_mpss": 0.42, "vert_mpss": -0.259, "yaw_dps": 2.73}, "brakes": {"wheelBrakes": "00", "traction": "unavailable", "abs": "unavailable", "scs": "unavailable", "brakeBoost": "unavailable", "auxBrakes": "unavailable"}, "size": {"width": 175, "length": 470}, "X_m": 124.381, "Y_m": 131.049, "Z_m": 0.0, "T_s": -11.827, "speed_mps": 15.58, "heading_deg": 211.075}, "partII": [{"partII-Id": 0, "partII-Value": {"pathHistory": {"crumbData": [{"xOffset_m": -209.063, "yOffset_m": -238.477, "zOffset_m": 0.0, "tOffset_s": -2.2}, {"xOffset_m": -266.679, "yOffset_m": -344.83, "zOffset_m": 0.0, "tOffset_s": -11.2}, {"xOffset_m": -361.592, "yOffset_m": -531.628, "zOffset_m": -2.1, "tOffset_s": -31.6}]}, "pathPrediction": {"radiusOfCurve": 8337, "confidence": 155}}}, {"partII-Id": 2, "partII-Value": {"classification": 10, "vehicleData": {"height": 29, "mass": 37}}}]}}}, {"eventMsgSeqNum": 9, "bsmRecord": {"msgHeader": {"myRFLevel": 0, "authenticated": true}, "bsmMsg": {"coreData": {"msgCnt": 110, "id": "07D4FB56", "accuracy": {"semiMajor": 142, "semiMinor": 2, "orientation": 55338}, "transmission": "forwardGears", "angle": 127, "accelSet": {"long_mpss": -0.18, "lat_mpss": 0.38, "vert_mpss": -0.259, "yaw_dps": 2.73}, "brakes": {"wheelBrakes": "00", "traction": "unavailable", "abs": "unavailable", "scs": "unavailable", "brakeBoost": "unavailable", "auxBrakes": "unavailable"}, "size": {"width": 175, "length": 470}, "X_m": 115.22, "Y_m": 118.356, "Z_m": 0.0, "T_s": -10.827, "speed_mps": 15.46, "heading_deg": 213.975}, "partII": [{"partII-Id": 0, "partII-Value": {"pathHistory": {"crumbData": [{"xOffset_m": -209.063, "yOffset_m": -238.477, "zOffset_m": 0.0, "tOffset_s": -3.19}, {"xOffset_m": -266.679, "yOffset_m": -344.83, "zOffset_m": 0.0, "tOffset_s": -12.19}, {"xOffset_m": -361.592, "yOffset_m": -531.628, "zOffset_m": -2.1, "tOffset_s": -32.6}]}, "pathPrediction": {"radiusOfCurve": 4277, "confidence": 195}}}, {"partII-Id": 2, "partII-Value": {"classification": 10, "vehicleData": {"height": 29, "mass": 37}}}]}}}, {"eventMsgSeqNum": 10, "bsmRecord": {"msgHeader": {"myRFLevel": 0, "authenticated": true}, "bsmMsg": {"coreData": {"msgCnt": 121, "id": "07D4FB56", "accuracy": {"semiMajor": 146, "semiMinor": 2, "orientation": 56006}, "transmission": "forwardGears", "angle": 127, "accelSet": {"long_mpss": -0.1, "lat_mpss": 0.61, "vert_mpss": -0.259, "yaw_dps": 3.24}, "brakes": {"wheelBrakes": "00", "traction": "unavailable", "abs": "unavailable", "scs": "unavailable", "brakeBoost": "unavailable", "auxBrakes": "unavailable"}, "size": {"width": 175, "length": 470}, "X_m": 104.447, "Y_m": 105.074, "Z_m": 0.0, "T_s": -9.727, "speed_mps": 15.34, "heading_deg": 217.65}, "partII": [{"partII-Id": 0, "partII-Value": {"pathHistory": {"crumbData": [{"xOffset_m": -180.541, "yOffset_m": -195.667, "zOffset_m": 0.0, "tOffset_s": -1.0}, {"xOffset_m": -209.071, "yOffset_m": -238.466, "zOffset_m": 0.0, "tOffset_s": -4.29}, {"xOffset_m": -266.687, "yOffset_m": -344.83, "zOffset_m": 0.0, "tOffset_s": -13.29}, {"xOffset_m": -361.601, "yOffset_m": -531.628, "zOffset_m": -2.1, "tOffset_s": -33.7}]}, "pathPrediction": {"radiusOfCurve": 3291, "confidence": 179}}}, {"partII-Id": 2, "partII-Value": {"classification": 10, "vehicleData": {"height": 29, "mass": 37}}}]}}}, {"eventMsgSeqNum": 11, "bsmRecord": {"msgHeader": {"myRFLevel": 0, "authenticated": true}, "bsmMsg": {"coreData": {"msgCnt": 3, "id": "07D4FB56", "accuracy": {"semiMajor": 147, "semiMinor": 2, "orientation": 56695}, "transmission": "forwardGears", "angle": 127, "accelSet": {"long_mpss": -0.14, "lat_mpss": 0.65, "vert_mpss": -0.259, "yaw_dps": 3.66}, "brakes": {"wheelBrakes": "00", "traction": "unavailable", "abs": "unavailable", "scs": "unavailable", "brakeBoost": "unavailable", "auxBrakes": "unavailable"}, "size": {"width": 175, "length": 470}, "X_m": 93.707, "Y_m": 93.692, "Z_m": 0.0, "T_s": -8.727, "speed_mps": 15.38, "heading_deg": 221.438}, "partII": [{"partII-Id": 0, "partII-Value": {"pathHistory": {"crumbData": [{"xOffset_m": -180.541, "yOffset_m": -195.667, "zOffset_m": 0.0, "tOffset_s": -2.0}, {"xOffset_m": -209.063, "yOffset_m": -238.477, "zOffset_m": 0.0, "tOffset_s": -5.29}, {"xOffset_m": -266.679, "yOffset_m": -344.83, "zOffset_m": 0.0, "tOffset_s": -14.3}, {"xOffset_m": -361.601, "yOffset_m": -531.628, "zOffset_m": -2.1, "tOffset_s": -34.7}]}, "pathPrediction": {"radiusOfCurve": 2782, "confidence": 173}}}, {"partII-Id": 2, "partII-Value": {"classification": 10, "vehicleData": {"height": 29, "mass": 37}}}]}}}, {"eventMsgSeqNum": 12, "bsmRecord": {"msgHeader": {"myRFLevel": 0, "authenticated": true}, "bsmMsg": {"coreData": {"msgCnt": 13, "id": "07D4FB56", "accuracy": {"semiMajor": 150, "semiMinor": 2, "orientation": 57252}, "transmission": "forwardGears", "angle": 127, "accelSet": {"long_mpss": -0.1, "lat_mpss": 0.38, "vert_mpss": -0.259, "yaw_dps": 2.22}, "brakes": {"wheelBrakes": "00", "traction": "unavailable", "abs": "unavailable", "scs": "unavailable", "brakeBoost": "unavailable", "auxBrakes": "unavailable"}, "size": {"width": 175, "length": 470}, "X_m": 82.367, "Y_m": 82.853, "Z_m": 0.0, "T_s": -7.727, "speed_mps": 15.48, "heading_deg": 224.488}, "partII": [{"partII-Id": 0, "partII-Value": {"pathHistory": {"crumbData": [{"xOffset_m": -155.439, "yOffset_m": -167.872, "zOffset_m": 0.0, "tOffset_s": -0.59}, {"xOffset_m": -180.541, "yOffset_m": -195.667, "zOffset_m": 0.0, "tOffset_s": -2.99}, {"xOffset_m": -209.071, "yOffset_m": -238.477, "zOffset_m": 0.0, "tOffset_s": -6.29}, {"xOffset_m": -266.687, "yOffset_m": -344.83, "zOffset_m": 0.0, "tOffset_s": -15.29}]}, "pathPrediction": {"radiusOfCurve": 2667, "confidence": 153}}}, {"partII-Id": 2, "partII-Value": {"classification": 10, "vehicleData": {"height": 29, "mass": 37}}}]}}}, {"eventMsgSeqNum": 13, "bsmRecord": {"msgHeader": {"myRFLevel": 0, "authenticated": true}, "bsmMsg": {"coreData": {"msgCnt": 23, "id": "07D4FB56", "accuracy": {"semiMajor": 152, "semiMinor": 2, "orientation": 57557}, "transmission": "forwardGears", "angle": 127, "accelSet": {"long_mpss": 0.05, "lat_mpss": 0.17, "vert_mpss": -0.259, "yaw_dps": 1.8900000000000001}, "brakes": {"wheelBrakes": "00", "traction": "unavailable", "abs": "unavailable", "scs": "unavailable", "brakeBoost": "unavailable", "auxBrakes": "unavailable"}, "size": {"width": 175, "length": 470}, "X_m": 70.723, "Y_m": 72.315, "Z_m": 0.0, "T_s": -6.727, "speed_mps": 15.4, "heading_deg": 226.163}, "partII": [{"partII-Id": 0, "partII-Value": {"pathHistory": {"crumbData": [{"xOffset_m": -155.439, "yOffset_m": -167.872, "zOffset_m": 0.0, "tOffset_s": -1.6}, {"xOffset_m": -180.541, "yOffset_m": -195.667, "zOffset_m": 0.0, "tOffset_s": -4.0}, {"xOffset_m": -209.071, "yOffset_m": -238.477, "zOffset_m": 0.0, "tOffset_s": -7.3}, {"xOffset_m": -266.687, "yOffset_m": -344.83, "zOffset_m": 0.0, "tOffset_s": -16.3}]}, "pathPrediction": {"radiusOfCurve": 3673, "confidence": 179}}}, {"partII-Id": 2, "partII-Value": {"classification": 10, "vehicleData": {"height": 29, "mass": 37}}}]}}}, {"eventMsgSeqNum": 14, "bsmRecord": {"msgHeader": {"myRFLevel": 0, "authenticated": true}, "bsmMsg": {"coreData": {"msgCnt": 33, "id": "07D4FB56", "accuracy": {"semiMajor": 156, "semiMinor": 2, "orientation": 57882}, "transmission": "forwardGears", "angle": 127, "accelSet": {"long_mpss": -0.1, "lat_mpss": 0.07, "vert_mpss": -0.259, "yaw_dps": 1.5}, "brakes": {"wheelBrakes": "00", "traction": "unavailable", "abs": "unavailable", "scs": "unavailable", "brakeBoost": "unavailable", "auxBrakes": "unavailable"}, "size": {"width": 175, "length": 470}, "X_m": 58.987, "Y_m": 62.098, "Z_m": 0.0, "T_s": -5.727, "speed_mps": 15.26, "heading_deg": 227.95}, "partII": [{"partII-Id": 0, "partII-Value": {"pathHistory": {"crumbData": [{"xOffset_m": -155.439, "yOffset_m": -167.872, "zOffset_m": 0.0, "tOffset_s": -2.6}, {"xOffset_m": -180.541, "yOffset_m": -195.667, "zOffset_m": 0.0, "tOffset_s": -5.0}, {"xOffset_m": -209.071, "yOffset_m": -238.466, "zOffset_m": 0.0, "tOffset_s": -8.3}, {"xOffset_m": -266.687, "yOffset_m": -344.83, "zOffset_m": 0.0, "tOffset_s": -17.3}]}, "pathPrediction": {"radiusOfCurve": 4524, "confidence": 182}}}, {"partII-Id": 2, "partII-Value": {"classification": 10, "vehicleData": {"height": 29, "mass": 37}}}]}}}, {"eventMsgSeqNum": 15, "bsmRecord": {"msgHeader": {"myRFLevel": 0, "authenticated": true}, "bsmMsg": {"coreData": {"msgCnt": 43, "id": "07D4FB56", "accuracy": {"semiMajor": 160, "semiMinor": 3, "orientation": 58026}, "transmission": "forwardGears", "angle": 127, "accelSet": {"long_mpss": -0.1, "lat_mpss": -0.34, "vert_mpss": -0.259, "yaw_dps": 0.0}, "brakes": {"wheelBrakes": "00", "traction": "unavailable", "abs": "unavailable", "scs": "unavailable", "brakeBoost": "unavailable", "auxBrakes": "unavailable"}, "size": {"width": 175, "length": 470}, "X_m": 47.335, "Y_m": 52.148, "Z_m": 0.0, "T_s": -4.727, "speed_mps": 15.02, "heading_deg": 228.75}, "partII": [{"partII-Id": 0, "partII-Value": {"pathHistory": {"crumbData": [{"xOffset_m": -155.439, "yOffset_m": -167.883, "zOffset_m": 0.0, "tOffset_s": -3.59}, {"xOffset_m": -180.541, "yOffset_m": -195.667, "zOffset_m": 0.0, "tOffset_s": -5.99}, {"xOffset_m": -209.071, "yOffset_m": -238.477, "zOffset_m": 0.0, "tOffset_s": -9.29}, {"xOffset_m": -266.687, "yOffset_m": -344.841, "zOffset_m": 0.0, "tOffset_s": -18.29}]}, "pathPrediction": {"radiusOfCurve": 5873, "confidence": 131}}}, {"partII-Id": 2, "partII-Value": {"classification": 10, "vehicleData": {"height": 29, "mass": 37}}}]}}}, {"eventMsgSeqNum": 16, "bsmRecord": {"msgHeader": {"myRFLevel": 0, "authenticated": true}, "bsmMsg": {"coreData": {"msgCnt": 53, "id": "07D4FB56", "accuracy": {"semiMajor": 162, "semiMinor": 3, "orientation": 57915}, "transmission": "forwardGears", "angle": 127, "accelSet": {"long_mpss": -0.18, "lat_mpss": -0.14, "vert_mpss": -0.259, "yaw_dps": -0.32}, "brakes": {"wheelBrakes": "00", "traction": "unavailable", "abs": "unavailable", "scs": "unavailable", "brakeBoost": "unavailable", "auxBrakes": "unavailable"}, "size": {"width": 175, "length": 470}, "X_m": 36.021, "Y_m": 42.11, "Z_m": 0.0, "T_s": -3.727, "speed_mps": 14.88, "heading_deg": 228.138}, "partII": [{"partII-Id": 0, "partII-Value": {"pathHistory": {"crumbData": [{"xOffset_m": -155.439, "yOffset_m": -167.872, "zOffset_m": 0.0, "tOffset_s": -4.6}, {"xOffset_m": -180.541, "yOffset_m": -195.667, "zOffset_m": 0.0, "tOffset_s": -7.0}, {"xOffset_m": -209.071, "yOffset_m": -238.477, "zOffset_m": 0.0, "tOffset_s": -10.29}, {"xOffset_m": -266.687, "yOffset_m": -344.83, "zOffset_m": 0.0, "tOffset_s": -19.3}]}, "pathPrediction": {"radiusOfCurve": 23030, "confidence": 194}}}, {"partII-Id": 2, "partII-Value": {"classification": 10, "vehicleData": {"height": 29, "mass": 37}}}]}}}, {"eventMsgSeqNum": 17, "bsmRecord": {"msgHeader": {"myRFLevel": 0, "authenticated": true}, "bsmMsg": {"coreData": {"msgCnt": 63, "id": "07D4FB56", "accuracy": {"semiMajor": 164, "semiMinor": 3, "orientation": 57838}, "transmission": "forwardGears", "angle": 127, "accelSet": {"long_mpss": -0.34, "lat_mpss": -0.24, "vert_mpss": -0.259, "yaw_dps": -0.04}, "brakes": {"wheelBrakes": "00", "traction": "unavailable", "abs": "unavailable", "scs": "unavailable", "brakeBoost": "unavailable", "auxBrakes": "unavailable"}, "size": {"width": 175, "length": 470}, "X_m": 25.128, "Y_m": 31.971, "Z_m": 0.0, "T_s": -2.727, "speed_mps": 14.7, "heading_deg": 227.713}, "partII": [{"partII-Id": 0, "partII-Value": {"pathHistory": {"crumbData": [{"xOffset_m": -155.439, "yOffset_m": -167.883, "zOffset_m": 0.0, "tOffset_s": -5.59}, {"xOffset_m": -180.541, "yOffset_m": -195.667, "zOffset_m": 0.0, "tOffset_s": -8.0}, {"xOffset_m": -209.071, "yOffset_m": -238.477, "zOffset_m": 0.0, "tOffset_s": -11.29}, {"xOffset_m": -266.687, "yOffset_m": -344.83, "zOffset_m": 0.0, "tOffset_s": -20.29}]}, "pathPrediction": {"radiusOfCurve": 32767, "confidence": 197}}}, {"partII-Id": 2, "partII-Value": {"classification": 10, "vehicleData": {"height": 29, "mass": 37}}}]}}}, {"eventMsgSeqNum": 18, "bsmRecord": {"msgHeader": {"myRFLevel": 0, "authenticated": true}, "bsmMsg": {"coreData": {"msgCnt": 73, "id": "07D4FB56", "accuracy": {"semiMajor": 162, "semiMinor": 3, "orientation": 57827}, "transmission": "forwardGears", "angle": 127, "accelSet": {"long_mpss": -0.1, "lat_mpss": -0.12, "vert_mpss": -0.259, "yaw_dps": 0.25}, "brakes": {"wheelBrakes": "00", "traction": "unavailable", "abs": "unavailable", "scs": "unavailable", "brakeBoost": "unavailable", "auxBrakes": "unavailable"}, "size": {"width": 175, "length": 470}, "X_m": 14.624, "Y_m": 21.765, "Z_m": 0.0, "T_s": -1.727, "speed_mps": 14.5, "heading_deg": 227.65}, "partII": [{"partII-Id": 0, "partII-Value": {"pathHistory": {"crumbData": [{"xOffset_m": -155.439, "yOffset_m": -167.883, "zOffset_m": 0.0, "tOffset_s": -6.6}, {"xOffset_m": -180.541, "yOffset_m": -195.667, "zOffset_m": 0.0, "tOffset_s": -9.0}, {"xOffset_m": -209.071, "yOffset_m": -238.477, "zOffset_m": 0.0, "tOffset_s": -12.3}, {"xOffset_m": -266.687, "yOffset_m": -344.83, "zOffset_m": 0.0, "tOffset_s": -21.3}]}, "pathPrediction": {"radiusOfCurve": 32767, "confidence": 182}}}, {"partII-Id": 2, "partII-Value": {"classification": 10, "vehicleData": {"height": 29, "mass": 37}}}]}}}, {"eventMsgSeqNum": 19, "bsmRecord": {"msgHeader": {"myRFLevel": 0, "authenticated": true}, "bsmMsg": {"coreData": {"msgCnt": 83, "id": "07D4FB56", "accuracy": {"semiMajor": 99, "semiMinor": 3, "orientation": 57512}, "transmission": "forwardGears", "angle": 127, "accelSet": {"long_mpss": 0.05, "lat_mpss": -0.03, "vert_mpss": -0.259, "yaw_dps": 0.16}, "brakes": {"wheelBrakes": "00", "traction": "unavailable", "abs": "unavailable", "scs": "unavailable", "brakeBoost": "unavailable", "auxBrakes": "unavailable"}, "size": {"width": 175, "length": 470}, "X_m": 8.309, "Y_m": 8.173, "Z_m": 0.0, "T_s": -0.727, "speed_mps": 14.52, "heading_deg": 225.925}, "partII": [{"partII-Id": 0, "partII-Value": {"pathHistory": {"crumbData": [{"xOffset_m": -78.763, "yOffset_m": -92.681, "zOffset_m": 0.0, "tOffset_s": -0.49}, {"xOffset_m": -80.849, "yOffset_m": -100.332, "zOffset_m": 0.0, "tOffset_s": -0.99}, {"xOffset_m": -155.431, "yOffset_m": -167.872, "zOffset_m": 0.0, "tOffset_s": -7.59}, {"xOffset_m": -180.541, "yOffset_m": -195.667, "zOffset_m": 0.0, "tOffset_s": -10.0}, {"xOffset_m": -209.063, "yOffset_m": -238.477, "zOffset_m": 0.0, "tOffset_s": -13.29}, {"xOffset_m": -266.679, "yOffset_m": -344.83, "zOffset_m": 0.0, "tOffset_s": -22.29}]}, "pathPrediction": {"radiusOfCurve": 32767, "confidence": 198}}}, {"partII-Id": 2, "partII-Value": {"classification": 10, "vehicleData": {"height": 29, "mass": 37}}}]}}}, {"eventMsgSeqNum": 20, "bsmRecord": {"msgHeader": {"myRFLevel": 0, "authenticated": true}, "bsmMsg": {"coreData": {"msgCnt": 91, "id": "07D4FB56", "accuracy": {"semiMajor": 96, "semiMinor": 3, "orientation": 57524}, "transmission": "forwardGears", "angle": 127, "accelSet": {"long_mpss": -0.28, "lat_mpss": 0.11, "vert_mpss": -0.259, "yaw_dps": 0.04}, "brakes": {"wheelBrakes": "00", "traction": "unavailable", "abs": "unavailable", "scs": "unavailable", "brakeBoost": "unavailable", "auxBrakes": "unavailable"}, "size": {"width": 175, "length": 470}, "X_m": 0.0, "Y_m": 0.0, "Z_m": 0.0, "T_s": 0.073, "speed_mps": 14.3, "heading_deg": 225.988}, "partII": [{"partII-Id": 0, "partII-Value": {"pathHistory": {"crumbData": [{"xOffset_m": -68.344, "yOffset_m": -80.554, "zOffset_m": 0.0, "tOffset_s": -0.2}, {"xOffset_m": -78.763, "yOffset_m": -92.681, "zOffset_m": 0.0, "tOffset_s": -1.3}, {"xOffset_m": -80.849, "yOffset_m": -100.332, "zOffset_m": 0.0, "tOffset_s": -1.8}, {"xOffset_m": -155.439, "yOffset_m": -167.872, "zOffset_m": 0.0, "tOffset_s": -8.4}, {"xOffset_m": -180.541, "yOffset_m": -195.667, "zOffset_m": 0.0, "tOffset_s": -10.8}, {"xOffset_m": -209.071, "yOffset_m": -238.477, "zOffset_m": 0.0, "tOffset_s": -14.1}]}, "pathPrediction": {"radiusOfCurve": 32767, "confidence": 200}}}, {"partII-Id": 2, "partII-Value": {"classification": 10, "vehicleData": {"height": 29, "mass": 37}}}]}}}, {"eventMsgSeqNum": 21, "bsmRecord": {"msgHeader": {"myRFLevel": 0, "authenticated": true}, "bsmMsg": {"coreData": {"msgCnt": 101, "id": "07D4FB56", "accuracy": {"semiMajor": 87, "semiMinor": 3, "orientation": 57477}, "transmission": "forwardGears", "angle": 127, "accelSet": {"long_mpss": -1.1300000000000001, "lat_mpss": -0.1, "vert_mpss": -0.259, "yaw_dps": -0.08}, "brakes": {"wheelBrakes": "00", "traction": "unavailable", "abs": "unavailable", "scs": "unavailable", "brakeBoost": "unavailable", "auxBrakes": "unavailable"}, "size": {"width": 175, "length": 470}, "X_m": -9.803, "Y_m": -10.316, "Z_m": 0.0, "T_s": 1.073, "speed_mps": 13.58, "heading_deg": 225.725}, "partII": [{"partII-Id": 0, "partII-Value": {"pathHistory": {"crumbData": [{"xOffset_m": -68.344, "yOffset_m": -80.554, "zOffset_m": 0.0, "tOffset_s": -1.2}, {"xOffset_m": -78.755, "yOffset_m": -92.681, "zOffset_m": 0.0, "tOffset_s": -2.29}, {"xOffset_m": -80.849, "yOffset_m": -100.321, "zOffset_m": 0.0, "tOffset_s": -2.79}, {"xOffset_m": -155.431, "yOffset_m": -167.872, "zOffset_m": 0.0, "tOffset_s": -9.4}, {"xOffset_m": -180.541, "yOffset_m": -195.667, "zOffset_m": 0.0, "tOffset_s": -11.8}, {"xOffset_m": -209.063, "yOffset_m": -238.477, "zOffset_m": 0.0, "tOffset_s": -15.09}]}, "pathPrediction": {"radiusOfCurve": 32767, "confidence": 195}}}, {"partII-Id": 2, "partII-Value": {"classification": 10, "vehicleData": {"height": 29, "mass": 37}}}]}}}, {"eventMsgSeqNum": 22, "bsmRecord": {"msgHeader": {"myRFLevel": 0, "authenticated": true}, "bsmMsg": {"coreData": {"msgCnt": 111, "id": "07D4FB56", "accuracy": {"semiMajor": 76, "semiMinor": 3, "orientation": 57313}, "transmission": "forwardGears", "angle": 127, "accelSet": {"long_mpss": -1.46, "lat_mpss": -0.49, "vert_mpss": -0.259, "yaw_dps": -1.03}, "brakes": {"wheelBrakes": "00", "traction": "unavailable", "abs": "unavailable", "scs": "unavailable", "brakeBoost": "unavailable", "auxBrakes": "unavailable"}, "size": {"width": 175, "length": 470}, "X_m": -18.72, "Y_m": -19.933, "Z_m": 0.0, "T_s": 2.073, "speed_mps": 12.06, "heading_deg": 224.825}, "partII": [{"partII-Id": 0, "partII-Value": {"pathHistory": {"crumbData": [{"xOffset_m": -68.344, "yOffset_m": -80.554, "zOffset_m": 0.0, "tOffset_s": -2.2}, {"xOffset_m": -78.763, "yOffset_m": -92.681, "zOffset_m": 0.0, "tOffset_s": -3.3}, {"xOffset_m": -80.849, "yOffset_m": -100.321, "zOffset_m": 0.0, "tOffset_s": -3.8}, {"xOffset_m": -155.431, "yOffset_m": -167.872, "zOffset_m": 0.0, "tOffset_s": -10.4}, {"xOffset_m": -180.541, "yOffset_m": -195.667, "zOffset_m": 0.0, "tOffset_s": -12.8}, {"xOffset_m": -209.063, "yOffset_m": -238.466, "zOffset_m": 0.0, "tOffset_s": -16.1}]}, "pathPrediction": {"radiusOfCurve": 32767, "confidence": 142}}}, {"partII-Id": 2, "partII-Value": {"classification": 10, "vehicleData": {"height": 29, "mass": 37}}}]}}}, {"eventMsgSeqNum": 23, "bsmRecord": {"msgHeader": {"myRFLevel": 0, "authenticated": true}, "bsmMsg": {"coreData": {"msgCnt": 122, "id": "07D4FB56", "accuracy": {"semiMajor": 70, "semiMinor": 3, "orientation": 57108}, "transmission": "forwardGears", "angle": 127, "accelSet": {"long_mpss": -0.98, "lat_mpss": -0.12, "vert_mpss": -0.259, "yaw_dps": -1.01}, "brakes": {"wheelBrakes": "00", "traction": "unavailable", "abs": "unavailable", "scs": "unavailable", "brakeBoost": "unavailable", "auxBrakes": "unavailable"}, "size": {"width": 175, "length": 470}, "X_m": -27.788, "Y_m": -29.228, "Z_m": 0.0, "T_s": 3.173, "speed_mps": 11.12, "heading_deg": 223.7}, "partII": [{"partII-Id": 0, "partII-Value": {"pathHistory": {"crumbData": [{"xOffset_m": -68.335, "yOffset_m": -80.554, "zOffset_m": 0.0, "tOffset_s": -3.29}, {"xOffset_m": -78.755, "yOffset_m": -92.681, "zOffset_m": 0.0, "tOffset_s": -4.39}, {"xOffset_m": -80.84, "yOffset_m": -100.332, "zOffset_m": 0.0, "tOffset_s": -4.89}, {"xOffset_m": -155.431, "yOffset_m": -167.872, "zOffset_m": 0.0, "tOffset_s": -11.49}, {"xOffset_m": -180.533, "yOffset_m": -195.667, "zOffset_m": 0.0, "tOffset_s": -13.89}, {"xOffset_m": -209.063, "yOffset_m": -238.477, "zOffset_m": 0.0, "tOffset_s": -17.19}]}, "pathPrediction": {"radiusOfCurve": -9190, "confidence": 199}}}, {"partII-Id": 2, "partII-Value": {"classification": 10, "vehicleData": {"height": 29, "mass": 37}}}]}}}, {"eventMsgSeqNum": 24, "bsmRecord": {"msgHeader": {"myRFLevel": 0, "authenticated": true}, "bsmMsg": {"coreData": {"msgCnt": 3, "id": "07D4FB56", "accuracy": {"semiMajor": 63, "semiMinor": 3, "orientation": 56733}, "transmission": "forwardGears", "angle": 127, "accelSet": {"long_mpss": -0.61, "lat_mpss": -0.3, "vert_mpss": -0.259, "yaw_dps": -2.2}, "brakes": {"wheelBrakes": "00", "traction": "unavailable", "abs": "unavailable", "scs": "unavailable", "brakeBoost": "unavailable", "auxBrakes": "unavailable"}, "size": {"width": 175, "length": 470}, "X_m": -37.338, "Y_m": -39.222, "Z_m": 0.0, "T_s": 4.473, "speed_mps": 9.98, "heading_deg": 221.638}, "partII": [{"partII-Id": 0, "partII-Value": {"pathHistory": {"crumbData": [{"xOffset_m": -68.344, "yOffset_m": -80.554, "zOffset_m": 0.0, "tOffset_s": -4.59}, {"xOffset_m": -78.763, "yOffset_m": -92.692, "zOffset_m": 0.0, "tOffset_s": -5.69}, {"xOffset_m": -80.849, "yOffset_m": -100.332, "zOffset_m": 0.0, "tOffset_s": -6.19}, {"xOffset_m": -155.431, "yOffset_m": -167.883, "zOffset_m": 0.0, "tOffset_s": -12.79}, {"xOffset_m": -180.541, "yOffset_m": -195.667, "zOffset_m": 0.0, "tOffset_s": -15.19}, {"xOffset_m": -209.063, "yOffset_m": -238.477, "zOffset_m": 0.0, "tOffset_s": -18.49}]}, "pathPrediction": {"radiusOfCurve": -5273, "confidence": 156}}}, {"partII-Id": 2, "partII-Value": {"classification": 10, "vehicleData": {"height": 29, "mass": 37}}}]}}}, {"eventMsgSeqNum": 25, "bsmRecord": {"msgHeader": {"myRFLevel": 0, "authenticated": true}, "bsmMsg": {"coreData": {"msgCnt": 13, "id": "07D4FB56", "accuracy": {"semiMajor": 54, "semiMinor": 3, "orientation": 56316}, "transmission": "forwardGears", "angle": 127, "accelSet": {"long_mpss": -0.36, "lat_mpss": -0.36, "vert_mpss": -0.259, "yaw_dps": -2.52}, "brakes": {"wheelBrakes": "00", "traction": "unavailable", "abs": "unavailable", "scs": "unavailable", "brakeBoost": "unavailable", "auxBrakes": "unavailable"}, "size": {"width": 175, "length": 470}, "X_m": -43.679, "Y_m": -46.762, "Z_m": 0.0, "T_s": 5.473, "speed_mps": 9.56, "heading_deg": 219.35}, "partII": [{"partII-Id": 0, "partII-Value": {"pathHistory": {"crumbData": [{"xOffset_m": -68.344, "yOffset_m": -80.554, "zOffset_m": 0.0, "tOffset_s": -5.59}, {"xOffset_m": -78.763, "yOffset_m": -92.681, "zOffset_m": 0.0, "tOffset_s": -6.69}, {"xOffset_m": -80.849, "yOffset_m": -100.332, "zOffset_m": 0.0, "tOffset_s": -7.19}, {"xOffset_m": -155.439, "yOffset_m": -167.872, "zOffset_m": 0.0, "tOffset_s": -13.79}, {"xOffset_m": -180.541, "yOffset_m": -195.667, "zOffset_m": 0.0, "tOffset_s": -16.19}, {"xOffset_m": -209.071, "yOffset_m": -238.477, "zOffset_m": 0.0, "tOffset_s": -19.49}]}, "pathPrediction": {"radiusOfCurve": -3079, "confidence": 180}}}, {"partII-Id": 2, "partII-Value": {"classification": 10, "vehicleData": {"height": 29, "mass": 37}}}]}}}, {"eventMsgSeqNum": 26, "bsmRecord": {"msgHeader": {"myRFLevel": 0, "authenticated": true}, "bsmMsg": {"coreData": {"msgCnt": 23, "id": "07D4FB56", "accuracy": {"semiMajor": 48, "semiMinor": 3, "orientation": 56000}, "transmission": "forwardGears", "angle": 127, "accelSet": {"long_mpss": 0.44, "lat_mpss": -0.03, "vert_mpss": -0.259, "yaw_dps": -1.27}, "brakes": {"wheelBrakes": "00", "traction": "unavailable", "abs": "unavailable", "scs": "unavailable", "brakeBoost": "unavailable", "auxBrakes": "unavailable"}, "size": {"width": 175, "length": 470}, "X_m": -49.691, "Y_m": -54.369, "Z_m": 0.0, "T_s": 6.473, "speed_mps": 9.92, "heading_deg": 217.613}, "partII": [{"partII-Id": 0, "partII-Value": {"pathHistory": {"crumbData": [{"xOffset_m": -22.545, "yOffset_m": -31.804, "zOffset_m": 0.0, "tOffset_s": -0.99}, {"xOffset_m": -68.344, "yOffset_m": -80.554, "zOffset_m": 0.0, "tOffset_s": -6.59}, {"xOffset_m": -78.763, "yOffset_m": -92.681, "zOffset_m": 0.0, "tOffset_s": -7.69}, {"xOffset_m": -80.849, "yOffset_m": -100.332, "zOffset_m": 0.0, "tOffset_s": -8.19}, {"xOffset_m": -155.439, "yOffset_m": -167.883, "zOffset_m": 0.0, "tOffset_s": -14.79}, {"xOffset_m": -180.541, "yOffset_m": -195.667, "zOffset_m": 0.0, "tOffset_s": -17.19}]}, "pathPrediction": {"radiusOfCurve": -2729, "confidence": 145}}}, {"partII-Id": 2, "partII-Value": {"classification": 10, "vehicleData": {"height": 29, "mass": 37}}}]}}}, {"eventMsgSeqNum": 27, "bsmRecord": {"msgHeader": {"myRFLevel": 0, "authenticated": true}, "bsmMsg": {"coreData": {"msgCnt": 33, "id": "07D4FB56", "accuracy": {"semiMajor": 38, "semiMinor": 3, "orientation": 55711}, "transmission": "forwardGears", "angle": 127, "accelSet": {"long_mpss": -0.36, "lat_mpss": -0.03, "vert_mpss": -0.259, "yaw_dps": -1.3900000000000001}, "brakes": {"wheelBrakes": "00", "traction": "unavailable", "abs": "unavailable", "scs": "unavailable", "brakeBoost": "unavailable", "auxBrakes": "unavailable"}, "size": {"width": 175, "length": 470}, "X_m": -55.383, "Y_m": -62.631, "Z_m": 0.0, "T_s": 7.473, "speed_mps": 9.94, "heading_deg": 216.025}, "partII": [{"partII-Id": 0, "partII-Value": {"pathHistory": {"crumbData": [{"xOffset_m": -22.545, "yOffset_m": -31.804, "zOffset_m": 0.0, "tOffset_s": -1.99}, {"xOffset_m": -68.344, "yOffset_m": -80.554, "zOffset_m": 0.0, "tOffset_s": -7.59}, {"xOffset_m": -78.763, "yOffset_m": -92.681, "zOffset_m": 0.0, "tOffset_s": -8.69}, {"xOffset_m": -80.849, "yOffset_m": -100.332, "zOffset_m": 0.0, "tOffset_s": -9.19}, {"xOffset_m": -155.439, "yOffset_m": -167.872, "zOffset_m": 0.0, "tOffset_s": -15.79}, {"xOffset_m": -180.541, "yOffset_m": -195.667, "zOffset_m": 0.0, "tOffset_s": -18.19}]}, "pathPrediction": {"radiusOfCurve": -3292, "confidence": 187}}}, {"partII-Id": 2, "partII-Value": {"classification": 10, "vehicleData": {"height": 29, "mass": 37}}}]}}}, {"eventMsgSeqNum": 28, "bsmRecord": {"msgHeader": {"myRFLevel": 0, "authenticated": true}, "bsmMsg": {"coreData": {"msgCnt": 43, "id": "07D4FB56", "accuracy": {"semiMajor": 35, "semiMinor": 3, "orientation": 55301}, "transmission": "forwardGears", "angle": 127, "accelSet": {"long_mpss": -0.36, "lat_mpss": -0.16, "vert_mpss": -0.259, "yaw_dps": -2.19}, "brakes": {"wheelBrakes": "00", "traction": "unavailable", "abs": "unavailable", "scs": "unavailable", "brakeBoost": "unavailable", "auxBrakes": "unavailable"}, "size": {"width": 175, "length": 470}, "X_m": -60.981, "Y_m": -70.793, "Z_m": 0.0, "T_s": 8.473, "speed_mps": 9.64, "heading_deg": 213.775}, "partII": [{"partII-Id": 0, "partII-Value": {"pathHistory": {"crumbData": [{"xOffset_m": -22.545, "yOffset_m": -31.804, "zOffset_m": 0.0, "tOffset_s": -3.0}, {"xOffset_m": -68.344, "yOffset_m": -80.554, "zOffset_m": 0.0, "tOffset_s": -8.6}, {"xOffset_m": -78.763, "yOffset_m": -92.681, "zOffset_m": 0.0, "tOffset_s": -9.7}, {"xOffset_m": -80.849, "yOffset_m": -100.332, "zOffset_m": 0.0, "tOffset_s": -10.2}, {"xOffset_m": -155.439, "yOffset_m": -167.872, "zOffset_m": 0.0, "tOffset_s": -16.8}, {"xOffset_m": -180.541, "yOffset_m": -195.667, "zOffset_m": 0.0, "tOffset_s": -19.2}]}, "pathPrediction": {"radiusOfCurve": -3083, "confidence": 158}}}, {"partII-Id": 2, "partII-Value": {"classification": 10, "vehicleData": {"height": 29, "mass": 37}}}]}}}, {"eventMsgSeqNum": 29, "bsmRecord": {"msgHeader": {"myRFLevel": 0, "authenticated": true}, "bsmMsg": {"coreData": {"msgCnt": 53, "id": "07D4FB56", "accuracy": {"semiMajor": 35, "semiMinor": 3, "orientation": 55097}, "transmission": "forwardGears", "angle": 127, "accelSet": {"long_mpss": -0.72, "lat_mpss": -0.18, "vert_mpss": -0.259, "yaw_dps": -0.97}, "brakes": {"wheelBrakes": "00", "traction": "unavailable", "abs": "unavailable", "scs": "unavailable", "brakeBoost": "unavailable", "auxBrakes": "unavailable"}, "size": {"width": 175, "length": 470}, "X_m": -66.224, "Y_m": -78.566, "Z_m": 0.0, "T_s": 9.473, "speed_mps": 8.92, "heading_deg": 212.65}, "partII": [{"partII-Id": 0, "partII-Value": {"pathHistory": {"crumbData": [{"xOffset_m": -22.545, "yOffset_m": -31.804, "zOffset_m": 0.0, "tOffset_s": -4.0}, {"xOffset_m": -68.344, "yOffset_m": -80.565, "zOffset_m": 0.0, "tOffset_s": -9.6}, {"xOffset_m": -78.755, "yOffset_m": -92.692, "zOffset_m": 0.0, "tOffset_s": -10.69}, {"xOffset_m": -80.849, "yOffset_m": -100.332, "zOffset_m": 0.0, "tOffset_s": -11.19}, {"xOffset_m": -155.431, "yOffset_m": -167.883, "zOffset_m": 0.0, "tOffset_s": -17.8}, {"xOffset_m": -180.541, "yOffset_m": -195.667, "zOffset_m": 0.0, "tOffset_s": -20.2}]}, "pathPrediction": {"radiusOfCurve": -3115, "confidence": 161}}}, {"partII-Id": 2, "partII-Value": {"classification": 10, "vehicleData": {"height": 29, "mass": 37}}}]}}}]}